<?xml version="1.0" encoding="utf-8"?>
<EncounterTable Name="Phuabo Des Abysses - [01:13] 12:27:51">
    <Row>
        <EncId>b03e8c3a</EncId>
        <Ally>T</Ally>
        <Name>Daddy Fahr</Name>
        <StartTime>2020-11-15 12:27:51</StartTime>
        <EndTime>2020-11-15 12:29:03</EndTime>
        <Duration>72</Duration>
        <Damage>1031156</Damage>
        <DamagePerc>30%</DamagePerc>
        <Kills>1</Kills>
        <Healed>0</Healed>
        <HealedPerc>0%</HealedPerc>
        <CritHeals>0</CritHeals>
        <Heals>0</Heals>
        <CureDispels>0</CureDispels>
        <PowerDrain>0</PowerDrain>
        <PowerReplenish>0</PowerReplenish>
        <DPS>14321.6111111111</DPS>
        <EncDPS>14125.4246575342</EncDPS>
        <EncHPS>0</EncHPS>
        <Hits>160</Hits>
        <CritHits>38</CritHits>
        <Blocked>0</Blocked>
        <Misses>0</Misses>
        <Swings>160</Swings>
        <HealsTaken>49872</HealsTaken>
        <DamageTaken>0</DamageTaken>
        <Deaths>0</Deaths>
        <ToHit>100</ToHit>
        <CritDamPerc>24%</CritDamPerc>
        <CritHealPerc>0%</CritHealPerc>
        <CritTypes>0.0%L - 0.0%F - 0.0%M</CritTypes>
        <ThreatStr>+(0)0/-(0)0</ThreatStr>
        <ThreatDelta>0</ThreatDelta>
        <Job>Brd</Job>
        <ParryPct>0%</ParryPct>
        <BlockPct>0%</BlockPct>
        <IncToHit>NaN</IncToHit>
        <OverHealPct>0%</OverHealPct>
        <DirectHitPct>48.8%</DirectHitPct>
        <DirectHitCount>78</DirectHitCount>
        <CritDirectHitCount>20</CritDirectHitCount>
        <CritDirectHitPct>12.5%</CritDirectHitPct>
    </Row>
    <Row>
        <EncId>b03e8c3a</EncId>
        <Ally>F</Ally>
        <Name>Dambanha Des Abysses</Name>
        <StartTime>2020-11-15 12:27:52</StartTime>
        <EndTime>2020-11-15 12:28:59</EndTime>
        <Duration>67</Duration>
        <Damage>175200</Damage>
        <DamagePerc>--</DamagePerc>
        <Kills>0</Kills>
        <Healed>0</Healed>
        <HealedPerc>--</HealedPerc>
        <CritHeals>0</CritHeals>
        <Heals>0</Heals>
        <CureDispels>0</CureDispels>
        <PowerDrain>0</PowerDrain>
        <PowerReplenish>0</PowerReplenish>
        <DPS>2614.92537313433</DPS>
        <EncDPS>2400</EncDPS>
        <EncHPS>0</EncHPS>
        <Hits>39</Hits>
        <CritHits>1</CritHits>
        <Blocked>0</Blocked>
        <Misses>0</Misses>
        <Swings>39</Swings>
        <HealsTaken>0</HealsTaken>
        <DamageTaken>1837839</DamageTaken>
        <Deaths>4</Deaths>
        <ToHit>100</ToHit>
        <CritDamPerc>3%</CritDamPerc>
        <CritHealPerc>0%</CritHealPerc>
        <CritTypes>0.0%L - 0.0%F - 0.0%M</CritTypes>
        <ThreatStr>+(0)0/-(0)0</ThreatStr>
        <ThreatDelta>0</ThreatDelta>
        <Job />
        <ParryPct>0%</ParryPct>
        <BlockPct>0%</BlockPct>
        <IncToHit>100.00</IncToHit>
        <OverHealPct>0%</OverHealPct>
        <DirectHitPct>0.0%</DirectHitPct>
        <DirectHitCount>0</DirectHitCount>
        <CritDirectHitCount>0</CritDirectHitCount>
        <CritDirectHitPct>0.0%</CritDirectHitPct>
    </Row>
    <Row>
        <EncId>b03e8c3a</EncId>
        <Ally>T</Ally>
        <Name>Dragult Ironian</Name>
        <StartTime>2020-11-15 12:27:53</StartTime>
        <EndTime>2020-11-15 12:29:03</EndTime>
        <Duration>70</Duration>
        <Damage>556115</Damage>
        <DamagePerc>16%</DamagePerc>
        <Kills>1</Kills>
        <Healed>197647</Healed>
        <HealedPerc>69%</HealedPerc>
        <CritHeals>4</CritHeals>
        <Heals>19</Heals>
        <CureDispels>0</CureDispels>
        <PowerDrain>0</PowerDrain>
        <PowerReplenish>1600</PowerReplenish>
        <DPS>7944.5</DPS>
        <EncDPS>7618.01369863014</EncDPS>
        <EncHPS>2707.49315068493</EncHPS>
        <Hits>47</Hits>
        <CritHits>12</CritHits>
        <Blocked>0</Blocked>
        <Misses>0</Misses>
        <Swings>47</Swings>
        <HealsTaken>0</HealsTaken>
        <DamageTaken>19980</DamageTaken>
        <Deaths>0</Deaths>
        <ToHit>100</ToHit>
        <CritDamPerc>26%</CritDamPerc>
        <CritHealPerc>21%</CritHealPerc>
        <CritTypes>0.0%L - 0.0%F - 0.0%M</CritTypes>
        <ThreatStr>+(0)0/-(0)0</ThreatStr>
        <ThreatDelta>0</ThreatDelta>
        <Job>Ast</Job>
        <ParryPct>0%</ParryPct>
        <BlockPct>0%</BlockPct>
        <IncToHit>100.00</IncToHit>
        <OverHealPct>1%</OverHealPct>
        <DirectHitPct>2.1%</DirectHitPct>
        <DirectHitCount>1</DirectHitCount>
        <CritDirectHitCount>1</CritDirectHitCount>
        <CritDirectHitPct>2.1%</CritDirectHitPct>
    </Row>
    <Row>
        <EncId>b03e8c3a</EncId>
        <Ally>T</Ally>
        <Name>Étoile Terrestre (Dragult Ironian)</Name>
        <StartTime>2020-11-15 12:29:01</StartTime>
        <EndTime>2020-11-15 12:29:01</EndTime>
        <Duration>0</Duration>
        <Damage>9979</Damage>
        <DamagePerc>0%</DamagePerc>
        <Kills>0</Kills>
        <Healed>82580</Healed>
        <HealedPerc>28%</HealedPerc>
        <CritHeals>1</CritHeals>
        <Heals>2</Heals>
        <CureDispels>0</CureDispels>
        <PowerDrain>0</PowerDrain>
        <PowerReplenish>0</PowerReplenish>
        <DPS>∞</DPS>
        <EncDPS>136.698630136986</EncDPS>
        <EncHPS>1131.23287671233</EncHPS>
        <Hits>1</Hits>
        <CritHits>0</CritHits>
        <Blocked>0</Blocked>
        <Misses>0</Misses>
        <Swings>1</Swings>
        <HealsTaken>0</HealsTaken>
        <DamageTaken>0</DamageTaken>
        <Deaths>0</Deaths>
        <ToHit>100</ToHit>
        <CritDamPerc>0%</CritDamPerc>
        <CritHealPerc>50%</CritHealPerc>
        <CritTypes>0.0%L - 0.0%F - 0.0%M</CritTypes>
        <ThreatStr>+(0)0/-(0)0</ThreatStr>
        <ThreatDelta>0</ThreatDelta>
        <Job />
        <ParryPct>0%</ParryPct>
        <BlockPct>0%</BlockPct>
        <IncToHit>NaN</IncToHit>
        <OverHealPct>60%</OverHealPct>
        <DirectHitPct>0.0%</DirectHitPct>
        <DirectHitCount>0</DirectHitCount>
        <CritDirectHitCount>0</CritDirectHitCount>
        <CritDirectHitPct>0.0%</CritDirectHitPct>
    </Row>
    <Row>
        <EncId>b03e8c3a</EncId>
        <Ally>T</Ally>
        <Name>Momoko Azami</Name>
        <StartTime>2020-11-15 12:27:52</StartTime>
        <EndTime>2020-11-15 12:29:04</EndTime>
        <Duration>72</Duration>
        <Damage>996448</Damage>
        <DamagePerc>29%</DamagePerc>
        <Kills>1</Kills>
        <Healed>0</Healed>
        <HealedPerc>0%</HealedPerc>
        <CritHeals>0</CritHeals>
        <Heals>0</Heals>
        <CureDispels>0</CureDispels>
        <PowerDrain>0</PowerDrain>
        <PowerReplenish>0</PowerReplenish>
        <DPS>13839.5555555556</DPS>
        <EncDPS>13649.9726027397</EncDPS>
        <EncHPS>0</EncHPS>
        <Hits>67</Hits>
        <CritHits>10</CritHits>
        <Blocked>1</Blocked>
        <Misses>0</Misses>
        <Swings>68</Swings>
        <HealsTaken>0</HealsTaken>
        <DamageTaken>0</DamageTaken>
        <Deaths>0</Deaths>
        <ToHit>98.52941</ToHit>
        <CritDamPerc>15%</CritDamPerc>
        <CritHealPerc>0%</CritHealPerc>
        <CritTypes>0.0%L - 0.0%F - 0.0%M</CritTypes>
        <ThreatStr>+(0)0/-(0)0</ThreatStr>
        <ThreatDelta>0</ThreatDelta>
        <Job>Blm</Job>
        <ParryPct>0%</ParryPct>
        <BlockPct>0%</BlockPct>
        <IncToHit>0.00</IncToHit>
        <OverHealPct>0%</OverHealPct>
        <DirectHitPct>23.5%</DirectHitPct>
        <DirectHitCount>16</DirectHitCount>
        <CritDirectHitCount>1</CritDirectHitCount>
        <CritDirectHitPct>1.5%</CritDirectHitPct>
    </Row>
    <Row>
        <EncId>b03e8c3a</EncId>
        <Ally>F</Ally>
        <Name>Phuabo Des Abysses</Name>
        <StartTime>2020-11-15 12:28:31</StartTime>
        <EndTime>2020-11-15 12:28:56</EndTime>
        <Duration>25</Duration>
        <Damage>49880</Damage>
        <DamagePerc>--</DamagePerc>
        <Kills>0</Kills>
        <Healed>0</Healed>
        <HealedPerc>--</HealedPerc>
        <CritHeals>0</CritHeals>
        <Heals>0</Heals>
        <CureDispels>0</CureDispels>
        <PowerDrain>0</PowerDrain>
        <PowerReplenish>0</PowerReplenish>
        <DPS>1995.2</DPS>
        <EncDPS>683.287671232877</EncDPS>
        <EncHPS>0</EncHPS>
        <Hits>8</Hits>
        <CritHits>1</CritHits>
        <Blocked>0</Blocked>
        <Misses>0</Misses>
        <Swings>8</Swings>
        <HealsTaken>0</HealsTaken>
        <DamageTaken>931789</DamageTaken>
        <Deaths>1</Deaths>
        <ToHit>100</ToHit>
        <CritDamPerc>13%</CritDamPerc>
        <CritHealPerc>0%</CritHealPerc>
        <CritTypes>0.0%L - 0.0%F - 0.0%M</CritTypes>
        <ThreatStr>+(0)0/-(0)0</ThreatStr>
        <ThreatDelta>0</ThreatDelta>
        <Job />
        <ParryPct>0%</ParryPct>
        <BlockPct>0%</BlockPct>
        <IncToHit>100.00</IncToHit>
        <OverHealPct>0%</OverHealPct>
        <DirectHitPct>0.0%</DirectHitPct>
        <DirectHitCount>0</DirectHitCount>
        <CritDirectHitCount>0</CritDirectHitCount>
        <CritDirectHitPct>0.0%</CritDirectHitPct>
    </Row>
    <Row>
        <EncId>b03e8c3a</EncId>
        <Ally>F</Ally>
        <Name>Unknown</Name>
        <StartTime>2020-11-15 12:28:23</StartTime>
        <EndTime>2020-11-15 12:29:05</EndTime>
        <Duration>42</Duration>
        <Damage>0</Damage>
        <DamagePerc>--</DamagePerc>
        <Kills>0</Kills>
        <Healed>14186</Healed>
        <HealedPerc>--</HealedPerc>
        <CritHeals>0</CritHeals>
        <Heals>1</Heals>
        <CureDispels>0</CureDispels>
        <PowerDrain>0</PowerDrain>
        <PowerReplenish>0</PowerReplenish>
        <DPS>0</DPS>
        <EncDPS>0</EncDPS>
        <EncHPS>194.328767123288</EncHPS>
        <Hits>0</Hits>
        <CritHits>0</CritHits>
        <Blocked>0</Blocked>
        <Misses>0</Misses>
        <Swings>0</Swings>
        <HealsTaken>0</HealsTaken>
        <DamageTaken>0</DamageTaken>
        <Deaths>0</Deaths>
        <ToHit>NaN</ToHit>
        <CritDamPerc>0%</CritDamPerc>
        <CritHealPerc>0%</CritHealPerc>
        <CritTypes>-</CritTypes>
        <ThreatStr>+(0)0/-(0)0</ThreatStr>
        <ThreatDelta>0</ThreatDelta>
        <Job />
        <ParryPct>0%</ParryPct>
        <BlockPct>0%</BlockPct>
        <IncToHit>NaN</IncToHit>
        <OverHealPct>0%</OverHealPct>
        <DirectHitPct>0.0%</DirectHitPct>
        <DirectHitCount>0</DirectHitCount>
        <CritDirectHitCount>0</CritDirectHitCount>
        <CritDirectHitPct>0.0%</CritDirectHitPct>
    </Row>
    <Row>
        <EncId>b03e8c3a</EncId>
        <Ally>F</Ally>
        <Name>Xzomit Des Abysses</Name>
        <StartTime>2020-11-15 12:27:51</StartTime>
        <EndTime>2020-11-15 12:28:24</EndTime>
        <Duration>33</Duration>
        <Damage>77586</Damage>
        <DamagePerc>--</DamagePerc>
        <Kills>0</Kills>
        <Healed>0</Healed>
        <HealedPerc>--</HealedPerc>
        <CritHeals>0</CritHeals>
        <Heals>0</Heals>
        <CureDispels>0</CureDispels>
        <PowerDrain>0</PowerDrain>
        <PowerReplenish>0</PowerReplenish>
        <DPS>2351.09090909091</DPS>
        <EncDPS>1062.82191780822</EncDPS>
        <EncHPS>0</EncHPS>
        <Hits>13</Hits>
        <CritHits>1</CritHits>
        <Blocked>0</Blocked>
        <Misses>0</Misses>
        <Swings>13</Swings>
        <HealsTaken>0</HealsTaken>
        <DamageTaken>664222</DamageTaken>
        <Deaths>1</Deaths>
        <ToHit>100</ToHit>
        <CritDamPerc>8%</CritDamPerc>
        <CritHealPerc>0%</CritHealPerc>
        <CritTypes>0.0%L - 0.0%F - 0.0%M</CritTypes>
        <ThreatStr>+(0)0/-(0)0</ThreatStr>
        <ThreatDelta>0</ThreatDelta>
        <Job />
        <ParryPct>0%</ParryPct>
        <BlockPct>0%</BlockPct>
        <IncToHit>100.00</IncToHit>
        <OverHealPct>0%</OverHealPct>
        <DirectHitPct>0.0%</DirectHitPct>
        <DirectHitCount>0</DirectHitCount>
        <CritDirectHitCount>0</CritDirectHitCount>
        <CritDirectHitPct>0.0%</CritDirectHitPct>
    </Row>
    <Row>
        <EncId>b03e8c3a</EncId>
        <Ally>T</Ally>
        <Name>YOU</Name>
        <StartTime>2020-11-15 12:27:51</StartTime>
        <EndTime>2020-11-15 12:29:05</EndTime>
        <Duration>74</Duration>
        <Damage>840152</Damage>
        <DamagePerc>24%</DamagePerc>
        <Kills>1</Kills>
        <Healed>5709</Healed>
        <HealedPerc>1%</HealedPerc>
        <CritHeals>0</CritHeals>
        <Heals>1</Heals>
        <CureDispels>0</CureDispels>
        <PowerDrain>0</PowerDrain>
        <PowerReplenish>0</PowerReplenish>
        <DPS>11353.4054054054</DPS>
        <EncDPS>11508.9315068493</EncDPS>
        <EncHPS>78.2054794520548</EncHPS>
        <Hits>119</Hits>
        <CritHits>27</CritHits>
        <Blocked>0</Blocked>
        <Misses>0</Misses>
        <Swings>119</Swings>
        <HealsTaken>250250</HealsTaken>
        <DamageTaken>282686</DamageTaken>
        <Deaths>0</Deaths>
        <ToHit>100</ToHit>
        <CritDamPerc>23%</CritDamPerc>
        <CritHealPerc>0%</CritHealPerc>
        <CritTypes>0.0%L - 0.0%F - 0.0%M</CritTypes>
        <ThreatStr>+(0)0/-(0)0</ThreatStr>
        <ThreatDelta>0</ThreatDelta>
        <Job>Gnb</Job>
        <ParryPct>11%</ParryPct>
        <BlockPct>0%</BlockPct>
        <IncToHit>100.00</IncToHit>
        <OverHealPct>0%</OverHealPct>
        <DirectHitPct>0.0%</DirectHitPct>
        <DirectHitCount>0</DirectHitCount>
        <CritDirectHitCount>0</CritDirectHitCount>
        <CritDirectHitPct>0.0%</CritDirectHitPct>
    </Row>
</EncounterTable>