<?xml version="1.0" encoding="utf-8"?>
<EncounterTable Name="Voleur Spectral - [11:55] 23:15:54">
    <Row>
        <EncId>0eeb549e</EncId>
        <Ally>F</Ally>
        <Name>Barde Spectral</Name>
        <StartTime>2020-10-11 23:17:38</StartTime>
        <EndTime>2020-10-11 23:24:56</EndTime>
        <Duration>438</Duration>
        <Damage>277674</Damage>
        <DamagePerc>--</DamagePerc>
        <Kills>0</Kills>
        <Healed>0</Healed>
        <HealedPerc>--</HealedPerc>
        <CritHeals>0</CritHeals>
        <Heals>0</Heals>
        <CureDispels>0</CureDispels>
        <PowerDrain>0</PowerDrain>
        <PowerReplenish>0</PowerReplenish>
        <DPS>633.958904109589</DPS>
        <EncDPS>388.355244755245</EncDPS>
        <EncHPS>0</EncHPS>
        <Hits>63</Hits>
        <CritHits>3</CritHits>
        <Blocked>0</Blocked>
        <Misses>0</Misses>
        <Swings>63</Swings>
        <HealsTaken>0</HealsTaken>
        <DamageTaken>2400149</DamageTaken>
        <Deaths>4</Deaths>
        <ToHit>100</ToHit>
        <CritDamPerc>5%</CritDamPerc>
        <CritHealPerc>0%</CritHealPerc>
        <CritTypes>0.0%L - 0.0%F - 0.0%M</CritTypes>
        <ThreatStr>+(0)0/-(0)0</ThreatStr>
        <ThreatDelta>0</ThreatDelta>
        <Job />
        <ParryPct>0%</ParryPct>
        <BlockPct>0%</BlockPct>
        <IncToHit>100.00</IncToHit>
        <OverHealPct>0%</OverHealPct>
        <DirectHitPct>0.0%</DirectHitPct>
        <DirectHitCount>0</DirectHitCount>
        <CritDirectHitCount>0</CritDirectHitCount>
        <CritDirectHitPct>0.0%</CritDirectHitPct>
    </Row>
    <Row>
        <EncId>0eeb549e</EncId>
        <Ally>T</Ally>
        <Name>Blacho Witsch</Name>
        <StartTime>2020-10-11 23:15:58</StartTime>
        <EndTime>2020-10-11 23:28:05</EndTime>
        <Duration>727</Duration>
        <Damage>7392272</Damage>
        <DamagePerc>25%</DamagePerc>
        <Kills>7</Kills>
        <Healed>0</Healed>
        <HealedPerc>0%</HealedPerc>
        <CritHeals>0</CritHeals>
        <Heals>0</Heals>
        <CureDispels>0</CureDispels>
        <PowerDrain>0</PowerDrain>
        <PowerReplenish>0</PowerReplenish>
        <DPS>10168.1870701513</DPS>
        <EncDPS>10338.841958042</EncDPS>
        <EncHPS>0</EncHPS>
        <Hits>1352</Hits>
        <CritHits>294</CritHits>
        <Blocked>6</Blocked>
        <Misses>0</Misses>
        <Swings>1358</Swings>
        <HealsTaken>831096</HealsTaken>
        <DamageTaken>495174</DamageTaken>
        <Deaths>1</Deaths>
        <ToHit>99.55817</ToHit>
        <CritDamPerc>22%</CritDamPerc>
        <CritHealPerc>0%</CritHealPerc>
        <CritTypes>0.0%L - 0.0%F - 0.0%M</CritTypes>
        <ThreatStr>+(0)0/-(0)0</ThreatStr>
        <ThreatDelta>0</ThreatDelta>
        <Job>Smn</Job>
        <ParryPct>14%</ParryPct>
        <BlockPct>0%</BlockPct>
        <IncToHit>79.31</IncToHit>
        <OverHealPct>0%</OverHealPct>
        <DirectHitPct>25.1%</DirectHitPct>
        <DirectHitCount>341</DirectHitCount>
        <CritDirectHitCount>66</CritDirectHitCount>
        <CritDirectHitPct>4.9%</CritDirectHitPct>
    </Row>
    <Row>
        <EncId>0eeb549e</EncId>
        <Ally>F</Ally>
        <Name>Bombe Nécrotique</Name>
        <StartTime>2020-10-11 23:25:46</StartTime>
        <EndTime>2020-10-11 23:27:33</EndTime>
        <Duration>107</Duration>
        <Damage>505075</Damage>
        <DamagePerc>--</DamagePerc>
        <Kills>0</Kills>
        <Healed>0</Healed>
        <HealedPerc>--</HealedPerc>
        <CritHeals>0</CritHeals>
        <Heals>0</Heals>
        <CureDispels>0</CureDispels>
        <PowerDrain>0</PowerDrain>
        <PowerReplenish>0</PowerReplenish>
        <DPS>4720.32710280374</DPS>
        <EncDPS>706.398601398601</EncDPS>
        <EncHPS>0</EncHPS>
        <Hits>33</Hits>
        <CritHits>0</CritHits>
        <Blocked>0</Blocked>
        <Misses>0</Misses>
        <Swings>33</Swings>
        <HealsTaken>0</HealsTaken>
        <DamageTaken>0</DamageTaken>
        <Deaths>0</Deaths>
        <ToHit>100</ToHit>
        <CritDamPerc>0%</CritDamPerc>
        <CritHealPerc>0%</CritHealPerc>
        <CritTypes>-</CritTypes>
        <ThreatStr>+(0)0/-(0)0</ThreatStr>
        <ThreatDelta>0</ThreatDelta>
        <Job />
        <ParryPct>0%</ParryPct>
        <BlockPct>0%</BlockPct>
        <IncToHit>NaN</IncToHit>
        <OverHealPct>0%</OverHealPct>
        <DirectHitPct>0.0%</DirectHitPct>
        <DirectHitCount>0</DirectHitCount>
        <CritDirectHitCount>0</CritDirectHitCount>
        <CritDirectHitPct>0.0%</CritDirectHitPct>
    </Row>
    <Row>
        <EncId>0eeb549e</EncId>
        <Ally>T</Ally>
        <Name>Carbuncle Émeraude (Naaru Segawa)</Name>
        <StartTime>2020-10-11 23:16:08</StartTime>
        <EndTime>2020-10-11 23:24:46</EndTime>
        <Duration>518</Duration>
        <Damage>1670903</Damage>
        <DamagePerc>5%</DamagePerc>
        <Kills>3</Kills>
        <Healed>0</Healed>
        <HealedPerc>0%</HealedPerc>
        <CritHeals>0</CritHeals>
        <Heals>0</Heals>
        <CureDispels>0</CureDispels>
        <PowerDrain>0</PowerDrain>
        <PowerReplenish>0</PowerReplenish>
        <DPS>3225.68146718147</DPS>
        <EncDPS>2336.92727272727</EncDPS>
        <EncHPS>0</EncHPS>
        <Hits>394</Hits>
        <CritHits>55</CritHits>
        <Blocked>4</Blocked>
        <Misses>0</Misses>
        <Swings>398</Swings>
        <HealsTaken>15471</HealsTaken>
        <DamageTaken>0</DamageTaken>
        <Deaths>0</Deaths>
        <ToHit>98.99498</ToHit>
        <CritDamPerc>14%</CritDamPerc>
        <CritHealPerc>0%</CritHealPerc>
        <CritTypes>0.0%L - 0.0%F - 0.0%M</CritTypes>
        <ThreatStr>+(0)0/-(0)0</ThreatStr>
        <ThreatDelta>0</ThreatDelta>
        <Job />
        <ParryPct>0%</ParryPct>
        <BlockPct>0%</BlockPct>
        <IncToHit>20.00</IncToHit>
        <OverHealPct>0%</OverHealPct>
        <DirectHitPct>21.6%</DirectHitPct>
        <DirectHitCount>86</DirectHitCount>
        <CritDirectHitCount>16</CritDirectHitCount>
        <CritDirectHitPct>4.0%</CritDirectHitPct>
    </Row>
    <Row>
        <EncId>0eeb549e</EncId>
        <Ally>T</Ally>
        <Name>Carbuncle Rubis (Naaru Segawa)</Name>
        <StartTime>2020-10-11 23:19:15</StartTime>
        <EndTime>2020-10-11 23:27:29</EndTime>
        <Duration>494</Duration>
        <Damage>749967</Damage>
        <DamagePerc>2%</DamagePerc>
        <Kills>0</Kills>
        <Healed>0</Healed>
        <HealedPerc>0%</HealedPerc>
        <CritHeals>0</CritHeals>
        <Heals>0</Heals>
        <CureDispels>0</CureDispels>
        <PowerDrain>0</PowerDrain>
        <PowerReplenish>0</PowerReplenish>
        <DPS>1518.15182186235</DPS>
        <EncDPS>1048.9048951049</EncDPS>
        <EncHPS>0</EncHPS>
        <Hits>95</Hits>
        <CritHits>18</CritHits>
        <Blocked>0</Blocked>
        <Misses>0</Misses>
        <Swings>95</Swings>
        <HealsTaken>0</HealsTaken>
        <DamageTaken>0</DamageTaken>
        <Deaths>0</Deaths>
        <ToHit>100</ToHit>
        <CritDamPerc>19%</CritDamPerc>
        <CritHealPerc>0%</CritHealPerc>
        <CritTypes>0.0%L - 0.0%F - 0.0%M</CritTypes>
        <ThreatStr>+(0)0/-(0)0</ThreatStr>
        <ThreatDelta>0</ThreatDelta>
        <Job />
        <ParryPct>0%</ParryPct>
        <BlockPct>0%</BlockPct>
        <IncToHit>NaN</IncToHit>
        <OverHealPct>0%</OverHealPct>
        <DirectHitPct>26.3%</DirectHitPct>
        <DirectHitCount>25</DirectHitCount>
        <CritDirectHitCount>7</CritDirectHitCount>
        <CritDirectHitPct>7.4%</CritDirectHitPct>
    </Row>
    <Row>
        <EncId>0eeb549e</EncId>
        <Ally>F</Ally>
        <Name>Chevalier Dragon Spectral</Name>
        <StartTime>2020-10-11 23:17:46</StartTime>
        <EndTime>2020-10-11 23:25:00</EndTime>
        <Duration>434</Duration>
        <Damage>272896</Damage>
        <DamagePerc>--</DamagePerc>
        <Kills>0</Kills>
        <Healed>0</Healed>
        <HealedPerc>--</HealedPerc>
        <CritHeals>0</CritHeals>
        <Heals>0</Heals>
        <CureDispels>0</CureDispels>
        <PowerDrain>0</PowerDrain>
        <PowerReplenish>0</PowerReplenish>
        <DPS>628.792626728111</DPS>
        <EncDPS>381.672727272727</EncDPS>
        <EncHPS>0</EncHPS>
        <Hits>63</Hits>
        <CritHits>2</CritHits>
        <Blocked>0</Blocked>
        <Misses>0</Misses>
        <Swings>63</Swings>
        <HealsTaken>0</HealsTaken>
        <DamageTaken>2377596</DamageTaken>
        <Deaths>3</Deaths>
        <ToHit>100</ToHit>
        <CritDamPerc>3%</CritDamPerc>
        <CritHealPerc>0%</CritHealPerc>
        <CritTypes>0.0%L - 0.0%F - 0.0%M</CritTypes>
        <ThreatStr>+(0)0/-(0)0</ThreatStr>
        <ThreatDelta>0</ThreatDelta>
        <Job />
        <ParryPct>0%</ParryPct>
        <BlockPct>0%</BlockPct>
        <IncToHit>100.00</IncToHit>
        <OverHealPct>0%</OverHealPct>
        <DirectHitPct>0.0%</DirectHitPct>
        <DirectHitCount>0</DirectHitCount>
        <CritDirectHitCount>0</CritDirectHitCount>
        <CritDirectHitPct>0.0%</CritDirectHitPct>
    </Row>
    <Row>
        <EncId>0eeb549e</EncId>
        <Ally>F</Ally>
        <Name>Chevalier Sacré Spectral</Name>
        <StartTime>2020-10-11 23:16:00</StartTime>
        <EndTime>2020-10-11 23:23:36</EndTime>
        <Duration>456</Duration>
        <Damage>296670</Damage>
        <DamagePerc>--</DamagePerc>
        <Kills>0</Kills>
        <Healed>0</Healed>
        <HealedPerc>--</HealedPerc>
        <CritHeals>0</CritHeals>
        <Heals>0</Heals>
        <CureDispels>0</CureDispels>
        <PowerDrain>0</PowerDrain>
        <PowerReplenish>0</PowerReplenish>
        <DPS>650.592105263158</DPS>
        <EncDPS>414.923076923077</EncDPS>
        <EncHPS>0</EncHPS>
        <Hits>81</Hits>
        <CritHits>1</CritHits>
        <Blocked>0</Blocked>
        <Misses>0</Misses>
        <Swings>81</Swings>
        <HealsTaken>0</HealsTaken>
        <DamageTaken>3742063</DamageTaken>
        <Deaths>4</Deaths>
        <ToHit>100</ToHit>
        <CritDamPerc>1%</CritDamPerc>
        <CritHealPerc>0%</CritHealPerc>
        <CritTypes>0.0%L - 0.0%F - 0.0%M</CritTypes>
        <ThreatStr>+(0)0/-(0)0</ThreatStr>
        <ThreatDelta>0</ThreatDelta>
        <Job />
        <ParryPct>0%</ParryPct>
        <BlockPct>0%</BlockPct>
        <IncToHit>100.00</IncToHit>
        <OverHealPct>0%</OverHealPct>
        <DirectHitPct>0.0%</DirectHitPct>
        <DirectHitCount>0</DirectHitCount>
        <CritDirectHitCount>0</CritDirectHitCount>
        <CritDirectHitPct>0.0%</CritDirectHitPct>
    </Row>
    <Row>
        <EncId>0eeb549e</EncId>
        <Ally>F</Ally>
        <Name>Couteau De Poltron</Name>
        <StartTime>2020-10-11 23:20:14</StartTime>
        <EndTime>2020-10-11 23:20:15</EndTime>
        <Duration>1</Duration>
        <Damage>94810</Damage>
        <DamagePerc>--</DamagePerc>
        <Kills>0</Kills>
        <Healed>0</Healed>
        <HealedPerc>--</HealedPerc>
        <CritHeals>0</CritHeals>
        <Heals>0</Heals>
        <CureDispels>0</CureDispels>
        <PowerDrain>0</PowerDrain>
        <PowerReplenish>0</PowerReplenish>
        <DPS>94810</DPS>
        <EncDPS>132.601398601399</EncDPS>
        <EncHPS>0</EncHPS>
        <Hits>2</Hits>
        <CritHits>0</CritHits>
        <Blocked>0</Blocked>
        <Misses>0</Misses>
        <Swings>2</Swings>
        <HealsTaken>0</HealsTaken>
        <DamageTaken>0</DamageTaken>
        <Deaths>0</Deaths>
        <ToHit>100</ToHit>
        <CritDamPerc>0%</CritDamPerc>
        <CritHealPerc>0%</CritHealPerc>
        <CritTypes>-</CritTypes>
        <ThreatStr>+(0)0/-(0)0</ThreatStr>
        <ThreatDelta>0</ThreatDelta>
        <Job />
        <ParryPct>0%</ParryPct>
        <BlockPct>0%</BlockPct>
        <IncToHit>NaN</IncToHit>
        <OverHealPct>0%</OverHealPct>
        <DirectHitPct>0.0%</DirectHitPct>
        <DirectHitCount>0</DirectHitCount>
        <CritDirectHitCount>0</CritDirectHitCount>
        <CritDirectHitPct>0.0%</CritDirectHitPct>
    </Row>
    <Row>
        <EncId>0eeb549e</EncId>
        <Ally>T</Ally>
        <Name>Demi-Phénix (Blacho Witsch)</Name>
        <StartTime>2020-10-11 23:17:35</StartTime>
        <EndTime>2020-10-11 23:26:51</EndTime>
        <Duration>556</Duration>
        <Damage>881697</Damage>
        <DamagePerc>3%</DamagePerc>
        <Kills>0</Kills>
        <Healed>58602</Healed>
        <HealedPerc>0%</HealedPerc>
        <CritHeals>21</CritHeals>
        <Heals>84</Heals>
        <CureDispels>0</CureDispels>
        <PowerDrain>0</PowerDrain>
        <PowerReplenish>0</PowerReplenish>
        <DPS>1585.78597122302</DPS>
        <EncDPS>1233.14265734266</EncDPS>
        <EncHPS>81.9608391608392</EncHPS>
        <Hits>45</Hits>
        <CritHits>8</CritHits>
        <Blocked>0</Blocked>
        <Misses>0</Misses>
        <Swings>45</Swings>
        <HealsTaken>0</HealsTaken>
        <DamageTaken>0</DamageTaken>
        <Deaths>0</Deaths>
        <ToHit>100</ToHit>
        <CritDamPerc>18%</CritDamPerc>
        <CritHealPerc>25%</CritHealPerc>
        <CritTypes>0.0%L - 0.0%F - 0.0%M</CritTypes>
        <ThreatStr>+(0)0/-(0)0</ThreatStr>
        <ThreatDelta>0</ThreatDelta>
        <Job />
        <ParryPct>0%</ParryPct>
        <BlockPct>0%</BlockPct>
        <IncToHit>NaN</IncToHit>
        <OverHealPct>66%</OverHealPct>
        <DirectHitPct>22.2%</DirectHitPct>
        <DirectHitCount>10</DirectHitCount>
        <CritDirectHitCount>3</CritDirectHitCount>
        <CritDirectHitPct>6.7%</CritDirectHitPct>
    </Row>
    <Row>
        <EncId>0eeb549e</EncId>
        <Ally>T</Ally>
        <Name>Demi-Phénix (Naaru Segawa)</Name>
        <StartTime>2020-10-11 23:17:44</StartTime>
        <EndTime>2020-10-11 23:27:51</EndTime>
        <Duration>607</Duration>
        <Damage>1275427</Damage>
        <DamagePerc>4%</DamagePerc>
        <Kills>2</Kills>
        <Healed>60839</Healed>
        <HealedPerc>0%</HealedPerc>
        <CritHeals>18</CritHeals>
        <Heals>84</Heals>
        <CureDispels>0</CureDispels>
        <PowerDrain>0</PowerDrain>
        <PowerReplenish>0</PowerReplenish>
        <DPS>2101.19769357496</DPS>
        <EncDPS>1783.81398601399</EncDPS>
        <EncHPS>85.0895104895105</EncHPS>
        <Hits>70</Hits>
        <CritHits>10</CritHits>
        <Blocked>0</Blocked>
        <Misses>0</Misses>
        <Swings>70</Swings>
        <HealsTaken>0</HealsTaken>
        <DamageTaken>0</DamageTaken>
        <Deaths>0</Deaths>
        <ToHit>100</ToHit>
        <CritDamPerc>14%</CritDamPerc>
        <CritHealPerc>21%</CritHealPerc>
        <CritTypes>0.0%L - 0.0%F - 0.0%M</CritTypes>
        <ThreatStr>+(0)0/-(0)0</ThreatStr>
        <ThreatDelta>0</ThreatDelta>
        <Job />
        <ParryPct>0%</ParryPct>
        <BlockPct>0%</BlockPct>
        <IncToHit>NaN</IncToHit>
        <OverHealPct>68%</OverHealPct>
        <DirectHitPct>35.7%</DirectHitPct>
        <DirectHitCount>25</DirectHitCount>
        <CritDirectHitCount>5</CritDirectHitCount>
        <CritDirectHitPct>7.1%</CritDirectHitPct>
    </Row>
    <Row>
        <EncId>0eeb549e</EncId>
        <Ally>T</Ally>
        <Name>Echo Khama</Name>
        <StartTime>2020-10-11 23:15:54</StartTime>
        <EndTime>2020-10-11 23:27:49</EndTime>
        <Duration>715</Duration>
        <Damage>6961253</Damage>
        <DamagePerc>24%</DamagePerc>
        <Kills>3</Kills>
        <Healed>60353</Healed>
        <HealedPerc>0%</HealedPerc>
        <CritHeals>0</CritHeals>
        <Heals>4</Heals>
        <CureDispels>0</CureDispels>
        <PowerDrain>0</PowerDrain>
        <PowerReplenish>62500</PowerReplenish>
        <DPS>9736.01818181818</DPS>
        <EncDPS>9736.01818181818</EncDPS>
        <EncHPS>84.4097902097902</EncHPS>
        <Hits>1181</Hits>
        <CritHits>218</CritHits>
        <Blocked>0</Blocked>
        <Misses>0</Misses>
        <Swings>1181</Swings>
        <HealsTaken>3998991</HealsTaken>
        <DamageTaken>2663229</DamageTaken>
        <Deaths>0</Deaths>
        <ToHit>100</ToHit>
        <CritDamPerc>18%</CritDamPerc>
        <CritHealPerc>0%</CritHealPerc>
        <CritTypes>0.0%L - 0.0%F - 0.0%M</CritTypes>
        <ThreatStr>+(0)0/-(0)0</ThreatStr>
        <ThreatDelta>0</ThreatDelta>
        <Job>Pld</Job>
        <ParryPct>6%</ParryPct>
        <BlockPct>36%</BlockPct>
        <IncToHit>100.00</IncToHit>
        <OverHealPct>0%</OverHealPct>
        <DirectHitPct>10.9%</DirectHitPct>
        <DirectHitCount>129</DirectHitCount>
        <CritDirectHitCount>21</CritDirectHitCount>
        <CritDirectHitPct>1.8%</CritDirectHitPct>
    </Row>
    <Row>
        <EncId>0eeb549e</EncId>
        <Ally>F</Ally>
        <Name>Lutteur Spectral</Name>
        <StartTime>2020-10-11 23:17:26</StartTime>
        <EndTime>2020-10-11 23:23:17</EndTime>
        <Duration>351</Duration>
        <Damage>354086</Damage>
        <DamagePerc>--</DamagePerc>
        <Kills>0</Kills>
        <Healed>0</Healed>
        <HealedPerc>--</HealedPerc>
        <CritHeals>0</CritHeals>
        <Heals>0</Heals>
        <CureDispels>0</CureDispels>
        <PowerDrain>0</PowerDrain>
        <PowerReplenish>0</PowerReplenish>
        <DPS>1008.79202279202</DPS>
        <EncDPS>495.225174825175</EncDPS>
        <EncHPS>0</EncHPS>
        <Hits>84</Hits>
        <CritHits>3</CritHits>
        <Blocked>0</Blocked>
        <Misses>0</Misses>
        <Swings>84</Swings>
        <HealsTaken>0</HealsTaken>
        <DamageTaken>2964937</DamageTaken>
        <Deaths>5</Deaths>
        <ToHit>100</ToHit>
        <CritDamPerc>4%</CritDamPerc>
        <CritHealPerc>0%</CritHealPerc>
        <CritTypes>0.0%L - 0.0%F - 0.0%M</CritTypes>
        <ThreatStr>+(0)0/-(0)0</ThreatStr>
        <ThreatDelta>0</ThreatDelta>
        <Job />
        <ParryPct>0%</ParryPct>
        <BlockPct>0%</BlockPct>
        <IncToHit>100.00</IncToHit>
        <OverHealPct>0%</OverHealPct>
        <DirectHitPct>0.0%</DirectHitPct>
        <DirectHitCount>0</DirectHitCount>
        <CritDirectHitCount>0</CritDirectHitCount>
        <CritDirectHitPct>0.0%</CritDirectHitPct>
    </Row>
    <Row>
        <EncId>0eeb549e</EncId>
        <Ally>F</Ally>
        <Name>Lutteuse Spectrale</Name>
        <StartTime>2020-10-11 23:15:59</StartTime>
        <EndTime>2020-10-11 23:22:57</EndTime>
        <Duration>418</Duration>
        <Damage>99819</Damage>
        <DamagePerc>--</DamagePerc>
        <Kills>0</Kills>
        <Healed>0</Healed>
        <HealedPerc>--</HealedPerc>
        <CritHeals>0</CritHeals>
        <Heals>0</Heals>
        <CureDispels>0</CureDispels>
        <PowerDrain>0</PowerDrain>
        <PowerReplenish>0</PowerReplenish>
        <DPS>238.801435406699</DPS>
        <EncDPS>139.606993006993</EncDPS>
        <EncHPS>0</EncHPS>
        <Hits>28</Hits>
        <CritHits>0</CritHits>
        <Blocked>0</Blocked>
        <Misses>0</Misses>
        <Swings>28</Swings>
        <HealsTaken>0</HealsTaken>
        <DamageTaken>1291892</DamageTaken>
        <Deaths>2</Deaths>
        <ToHit>100</ToHit>
        <CritDamPerc>0%</CritDamPerc>
        <CritHealPerc>0%</CritHealPerc>
        <CritTypes>-</CritTypes>
        <ThreatStr>+(0)0/-(0)0</ThreatStr>
        <ThreatDelta>0</ThreatDelta>
        <Job />
        <ParryPct>0%</ParryPct>
        <BlockPct>0%</BlockPct>
        <IncToHit>100.00</IncToHit>
        <OverHealPct>0%</OverHealPct>
        <DirectHitPct>0.0%</DirectHitPct>
        <DirectHitCount>0</DirectHitCount>
        <CritDirectHitCount>0</CritDirectHitCount>
        <CritDirectHitPct>0.0%</CritDirectHitPct>
    </Row>
    <Row>
        <EncId>0eeb549e</EncId>
        <Ally>F</Ally>
        <Name>Mage Blanc Spectral</Name>
        <StartTime>2020-10-11 23:15:59</StartTime>
        <EndTime>2020-10-11 23:23:16</EndTime>
        <Duration>437</Duration>
        <Damage>107714</Damage>
        <DamagePerc>--</DamagePerc>
        <Kills>0</Kills>
        <Healed>0</Healed>
        <HealedPerc>--</HealedPerc>
        <CritHeals>0</CritHeals>
        <Heals>0</Heals>
        <CureDispels>0</CureDispels>
        <PowerDrain>0</PowerDrain>
        <PowerReplenish>0</PowerReplenish>
        <DPS>246.485125858124</DPS>
        <EncDPS>150.648951048951</EncDPS>
        <EncHPS>0</EncHPS>
        <Hits>22</Hits>
        <CritHits>0</CritHits>
        <Blocked>0</Blocked>
        <Misses>0</Misses>
        <Swings>22</Swings>
        <HealsTaken>0</HealsTaken>
        <DamageTaken>1263379</DamageTaken>
        <Deaths>2</Deaths>
        <ToHit>100</ToHit>
        <CritDamPerc>0%</CritDamPerc>
        <CritHealPerc>0%</CritHealPerc>
        <CritTypes>-</CritTypes>
        <ThreatStr>+(0)0/-(0)0</ThreatStr>
        <ThreatDelta>0</ThreatDelta>
        <Job />
        <ParryPct>0%</ParryPct>
        <BlockPct>0%</BlockPct>
        <IncToHit>100.00</IncToHit>
        <OverHealPct>0%</OverHealPct>
        <DirectHitPct>0.0%</DirectHitPct>
        <DirectHitCount>0</DirectHitCount>
        <CritDirectHitCount>0</CritDirectHitCount>
        <CritDirectHitPct>0.0%</CritDirectHitPct>
    </Row>
    <Row>
        <EncId>0eeb549e</EncId>
        <Ally>F</Ally>
        <Name>Mage Noir Spectral</Name>
        <StartTime>2020-10-11 23:15:59</StartTime>
        <EndTime>2020-10-11 23:16:43</EndTime>
        <Duration>44</Duration>
        <Damage>87797</Damage>
        <DamagePerc>--</DamagePerc>
        <Kills>0</Kills>
        <Healed>0</Healed>
        <HealedPerc>--</HealedPerc>
        <CritHeals>0</CritHeals>
        <Heals>0</Heals>
        <CureDispels>0</CureDispels>
        <PowerDrain>0</PowerDrain>
        <PowerReplenish>0</PowerReplenish>
        <DPS>1995.38636363636</DPS>
        <EncDPS>122.793006993007</EncDPS>
        <EncHPS>0</EncHPS>
        <Hits>15</Hits>
        <CritHits>0</CritHits>
        <Blocked>0</Blocked>
        <Misses>0</Misses>
        <Swings>15</Swings>
        <HealsTaken>0</HealsTaken>
        <DamageTaken>608685</DamageTaken>
        <Deaths>1</Deaths>
        <ToHit>100</ToHit>
        <CritDamPerc>0%</CritDamPerc>
        <CritHealPerc>0%</CritHealPerc>
        <CritTypes>-</CritTypes>
        <ThreatStr>+(0)0/-(0)0</ThreatStr>
        <ThreatDelta>0</ThreatDelta>
        <Job />
        <ParryPct>0%</ParryPct>
        <BlockPct>0%</BlockPct>
        <IncToHit>100.00</IncToHit>
        <OverHealPct>0%</OverHealPct>
        <DirectHitPct>0.0%</DirectHitPct>
        <DirectHitCount>0</DirectHitCount>
        <CritDirectHitCount>0</CritDirectHitCount>
        <CritDirectHitPct>0.0%</CritDirectHitPct>
    </Row>
    <Row>
        <EncId>0eeb549e</EncId>
        <Ally>T</Ally>
        <Name>Momoko Azami</Name>
        <StartTime>2020-10-11 23:15:55</StartTime>
        <EndTime>2020-10-11 23:28:03</EndTime>
        <Duration>728</Duration>
        <Damage>1974668</Damage>
        <DamagePerc>6%</DamagePerc>
        <Kills>6</Kills>
        <Healed>6560185</Healed>
        <HealedPerc>97%</HealedPerc>
        <CritHeals>81</CritHeals>
        <Heals>559</Heals>
        <CureDispels>0</CureDispels>
        <PowerDrain>0</PowerDrain>
        <PowerReplenish>19200</PowerReplenish>
        <DPS>2712.45604395604</DPS>
        <EncDPS>2761.77342657343</EncDPS>
        <EncHPS>9175.08391608392</EncHPS>
        <Hits>200</Hits>
        <CritHits>27</CritHits>
        <Blocked>5</Blocked>
        <Misses>0</Misses>
        <Swings>205</Swings>
        <HealsTaken>1286196</HealsTaken>
        <DamageTaken>669032</DamageTaken>
        <Deaths>0</Deaths>
        <ToHit>97.56097</ToHit>
        <CritDamPerc>14%</CritDamPerc>
        <CritHealPerc>14%</CritHealPerc>
        <CritTypes>0.0%L - 0.0%F - 0.0%M</CritTypes>
        <ThreatStr>+(0)0/-(0)0</ThreatStr>
        <ThreatDelta>0</ThreatDelta>
        <Job>Ast</Job>
        <ParryPct>0%</ParryPct>
        <BlockPct>0%</BlockPct>
        <IncToHit>85.71</IncToHit>
        <OverHealPct>42%</OverHealPct>
        <DirectHitPct>0.0%</DirectHitPct>
        <DirectHitCount>0</DirectHitCount>
        <CritDirectHitCount>0</CritDirectHitCount>
        <CritDirectHitPct>0.0%</CritDirectHitPct>
    </Row>
    <Row>
        <EncId>0eeb549e</EncId>
        <Ally>F</Ally>
        <Name>Mystagogue Spectrale</Name>
        <StartTime>2020-10-11 23:24:04</StartTime>
        <EndTime>2020-10-11 23:24:51</EndTime>
        <Duration>47</Duration>
        <Damage>124918</Damage>
        <DamagePerc>--</DamagePerc>
        <Kills>0</Kills>
        <Healed>0</Healed>
        <HealedPerc>--</HealedPerc>
        <CritHeals>0</CritHeals>
        <Heals>0</Heals>
        <CureDispels>0</CureDispels>
        <PowerDrain>0</PowerDrain>
        <PowerReplenish>0</PowerReplenish>
        <DPS>2657.82978723404</DPS>
        <EncDPS>174.71048951049</EncDPS>
        <EncHPS>0</EncHPS>
        <Hits>22</Hits>
        <CritHits>0</CritHits>
        <Blocked>0</Blocked>
        <Misses>0</Misses>
        <Swings>22</Swings>
        <HealsTaken>0</HealsTaken>
        <DamageTaken>1016356</DamageTaken>
        <Deaths>2</Deaths>
        <ToHit>100</ToHit>
        <CritDamPerc>0%</CritDamPerc>
        <CritHealPerc>0%</CritHealPerc>
        <CritTypes>-</CritTypes>
        <ThreatStr>+(0)0/-(0)0</ThreatStr>
        <ThreatDelta>0</ThreatDelta>
        <Job />
        <ParryPct>0%</ParryPct>
        <BlockPct>0%</BlockPct>
        <IncToHit>100.00</IncToHit>
        <OverHealPct>0%</OverHealPct>
        <DirectHitPct>0.0%</DirectHitPct>
        <DirectHitCount>0</DirectHitCount>
        <CritDirectHitCount>0</CritDirectHitCount>
        <CritDirectHitPct>0.0%</CritDirectHitPct>
    </Row>
    <Row>
        <EncId>0eeb549e</EncId>
        <Ally>F</Ally>
        <Name>Nécromancienne Spectrale</Name>
        <StartTime>2020-10-11 23:25:20</StartTime>
        <EndTime>2020-10-11 23:27:49</EndTime>
        <Duration>149</Duration>
        <Damage>683211</Damage>
        <DamagePerc>--</DamagePerc>
        <Kills>0</Kills>
        <Healed>0</Healed>
        <HealedPerc>--</HealedPerc>
        <CritHeals>0</CritHeals>
        <Heals>0</Heals>
        <CureDispels>0</CureDispels>
        <PowerDrain>0</PowerDrain>
        <PowerReplenish>0</PowerReplenish>
        <DPS>4585.30872483221</DPS>
        <EncDPS>955.53986013986</EncDPS>
        <EncHPS>0</EncHPS>
        <Hits>38</Hits>
        <CritHits>0</CritHits>
        <Blocked>0</Blocked>
        <Misses>0</Misses>
        <Swings>38</Swings>
        <HealsTaken>0</HealsTaken>
        <DamageTaken>5315935</DamageTaken>
        <Deaths>1</Deaths>
        <ToHit>100</ToHit>
        <CritDamPerc>0%</CritDamPerc>
        <CritHealPerc>0%</CritHealPerc>
        <CritTypes>-</CritTypes>
        <ThreatStr>+(0)0/-(0)0</ThreatStr>
        <ThreatDelta>0</ThreatDelta>
        <Job />
        <ParryPct>0%</ParryPct>
        <BlockPct>0%</BlockPct>
        <IncToHit>100.00</IncToHit>
        <OverHealPct>0%</OverHealPct>
        <DirectHitPct>0.0%</DirectHitPct>
        <DirectHitCount>0</DirectHitCount>
        <CritDirectHitCount>0</CritDirectHitCount>
        <CritDirectHitPct>0.0%</CritDirectHitPct>
    </Row>
    <Row>
        <EncId>0eeb549e</EncId>
        <Ally>F</Ally>
        <Name>Samouraï Spectral</Name>
        <StartTime>2020-10-11 23:16:05</StartTime>
        <EndTime>2020-10-11 23:23:23</EndTime>
        <Duration>438</Duration>
        <Damage>120253</Damage>
        <DamagePerc>--</DamagePerc>
        <Kills>0</Kills>
        <Healed>0</Healed>
        <HealedPerc>--</HealedPerc>
        <CritHeals>0</CritHeals>
        <Heals>0</Heals>
        <CureDispels>0</CureDispels>
        <PowerDrain>0</PowerDrain>
        <PowerReplenish>0</PowerReplenish>
        <DPS>274.550228310502</DPS>
        <EncDPS>168.186013986014</EncDPS>
        <EncHPS>0</EncHPS>
        <Hits>30</Hits>
        <CritHits>0</CritHits>
        <Blocked>0</Blocked>
        <Misses>0</Misses>
        <Swings>30</Swings>
        <HealsTaken>0</HealsTaken>
        <DamageTaken>1409312</DamageTaken>
        <Deaths>2</Deaths>
        <ToHit>100</ToHit>
        <CritDamPerc>0%</CritDamPerc>
        <CritHealPerc>0%</CritHealPerc>
        <CritTypes>-</CritTypes>
        <ThreatStr>+(0)0/-(0)0</ThreatStr>
        <ThreatDelta>0</ThreatDelta>
        <Job />
        <ParryPct>0%</ParryPct>
        <BlockPct>0%</BlockPct>
        <IncToHit>100.00</IncToHit>
        <OverHealPct>0%</OverHealPct>
        <DirectHitPct>0.0%</DirectHitPct>
        <DirectHitCount>0</DirectHitCount>
        <CritDirectHitCount>0</CritDirectHitCount>
        <CritDirectHitPct>0.0%</CritDirectHitPct>
    </Row>
    <Row>
        <EncId>0eeb549e</EncId>
        <Ally>F</Ally>
        <Name>Samouraï Spectrale</Name>
        <StartTime>2020-10-11 23:16:05</StartTime>
        <EndTime>2020-10-11 23:16:50</EndTime>
        <Duration>45</Duration>
        <Damage>79105</Damage>
        <DamagePerc>--</DamagePerc>
        <Kills>0</Kills>
        <Healed>0</Healed>
        <HealedPerc>--</HealedPerc>
        <CritHeals>0</CritHeals>
        <Heals>0</Heals>
        <CureDispels>0</CureDispels>
        <PowerDrain>0</PowerDrain>
        <PowerReplenish>0</PowerReplenish>
        <DPS>1757.88888888889</DPS>
        <EncDPS>110.636363636364</EncDPS>
        <EncHPS>0</EncHPS>
        <Hits>16</Hits>
        <CritHits>0</CritHits>
        <Blocked>0</Blocked>
        <Misses>0</Misses>
        <Swings>16</Swings>
        <HealsTaken>0</HealsTaken>
        <DamageTaken>692585</DamageTaken>
        <Deaths>1</Deaths>
        <ToHit>100</ToHit>
        <CritDamPerc>0%</CritDamPerc>
        <CritHealPerc>0%</CritHealPerc>
        <CritTypes>-</CritTypes>
        <ThreatStr>+(0)0/-(0)0</ThreatStr>
        <ThreatDelta>0</ThreatDelta>
        <Job />
        <ParryPct>0%</ParryPct>
        <BlockPct>0%</BlockPct>
        <IncToHit>100.00</IncToHit>
        <OverHealPct>0%</OverHealPct>
        <DirectHitPct>0.0%</DirectHitPct>
        <DirectHitCount>0</DirectHitCount>
        <CritDirectHitCount>0</CritDirectHitCount>
        <CritDirectHitPct>0.0%</CritDirectHitPct>
    </Row>
    <Row>
        <EncId>0eeb549e</EncId>
        <Ally>F</Ally>
        <Name>Unknown</Name>
        <StartTime>2020-10-11 23:17:45</StartTime>
        <EndTime>2020-10-11 23:27:53</EndTime>
        <Duration>608</Duration>
        <Damage>0</Damage>
        <DamagePerc>--</DamagePerc>
        <Kills>1</Kills>
        <Healed>56971</Healed>
        <HealedPerc>--</HealedPerc>
        <CritHeals>0</CritHeals>
        <Heals>6</Heals>
        <CureDispels>0</CureDispels>
        <PowerDrain>0</PowerDrain>
        <PowerReplenish>0</PowerReplenish>
        <DPS>0</DPS>
        <EncDPS>0</EncDPS>
        <EncHPS>79.6797202797203</EncHPS>
        <Hits>0</Hits>
        <CritHits>0</CritHits>
        <Blocked>0</Blocked>
        <Misses>0</Misses>
        <Swings>0</Swings>
        <HealsTaken>0</HealsTaken>
        <DamageTaken>0</DamageTaken>
        <Deaths>1</Deaths>
        <ToHit>NaN</ToHit>
        <CritDamPerc>0%</CritDamPerc>
        <CritHealPerc>0%</CritHealPerc>
        <CritTypes>-</CritTypes>
        <ThreatStr>+(0)0/-(0)0</ThreatStr>
        <ThreatDelta>0</ThreatDelta>
        <Job />
        <ParryPct>0%</ParryPct>
        <BlockPct>0%</BlockPct>
        <IncToHit>NaN</IncToHit>
        <OverHealPct>28%</OverHealPct>
        <DirectHitPct>0.0%</DirectHitPct>
        <DirectHitCount>0</DirectHitCount>
        <CritDirectHitCount>0</CritDirectHitCount>
        <CritDirectHitPct>0.0%</CritDirectHitPct>
    </Row>
    <Row>
        <EncId>0eeb549e</EncId>
        <Ally>F</Ally>
        <Name>Voleur Spectral</Name>
        <StartTime>2020-10-11 23:19:11</StartTime>
        <EndTime>2020-10-11 23:21:56</EndTime>
        <Duration>165</Duration>
        <Damage>1047967</Damage>
        <DamagePerc>--</DamagePerc>
        <Kills>0</Kills>
        <Healed>0</Healed>
        <HealedPerc>--</HealedPerc>
        <CritHeals>0</CritHeals>
        <Heals>0</Heals>
        <CureDispels>0</CureDispels>
        <PowerDrain>0</PowerDrain>
        <PowerReplenish>0</PowerReplenish>
        <DPS>6351.31515151515</DPS>
        <EncDPS>1465.68811188811</EncDPS>
        <EncHPS>0</EncHPS>
        <Hits>62</Hits>
        <CritHits>0</CritHits>
        <Blocked>0</Blocked>
        <Misses>0</Misses>
        <Swings>62</Swings>
        <HealsTaken>0</HealsTaken>
        <DamageTaken>5800922</DamageTaken>
        <Deaths>1</Deaths>
        <ToHit>100</ToHit>
        <CritDamPerc>0%</CritDamPerc>
        <CritHealPerc>0%</CritHealPerc>
        <CritTypes>-</CritTypes>
        <ThreatStr>+(0)0/-(0)0</ThreatStr>
        <ThreatDelta>0</ThreatDelta>
        <Job />
        <ParryPct>0%</ParryPct>
        <BlockPct>0%</BlockPct>
        <IncToHit>100.00</IncToHit>
        <OverHealPct>0%</OverHealPct>
        <DirectHitPct>0.0%</DirectHitPct>
        <DirectHitCount>0</DirectHitCount>
        <CritDirectHitCount>0</CritDirectHitCount>
        <CritDirectHitPct>0.0%</CritDirectHitPct>
    </Row>
    <Row>
        <EncId>0eeb549e</EncId>
        <Ally>T</Ally>
        <Name>YOU</Name>
        <StartTime>2020-10-11 23:16:06</StartTime>
        <EndTime>2020-10-11 23:27:53</EndTime>
        <Duration>707</Duration>
        <Damage>7977624</Damage>
        <DamagePerc>27%</DamagePerc>
        <Kills>4</Kills>
        <Healed>0</Healed>
        <HealedPerc>0%</HealedPerc>
        <CritHeals>0</CritHeals>
        <Heals>0</Heals>
        <CureDispels>0</CureDispels>
        <PowerDrain>0</PowerDrain>
        <PowerReplenish>0</PowerReplenish>
        <DPS>11283.7680339463</DPS>
        <EncDPS>11157.5160839161</EncDPS>
        <EncHPS>0</EncHPS>
        <Hits>1188</Hits>
        <CritHits>232</CritHits>
        <Blocked>2</Blocked>
        <Misses>0</Misses>
        <Swings>1190</Swings>
        <HealsTaken>665196</HealsTaken>
        <DamageTaken>324560</DamageTaken>
        <Deaths>0</Deaths>
        <ToHit>99.83193</ToHit>
        <CritDamPerc>20%</CritDamPerc>
        <CritHealPerc>0%</CritHealPerc>
        <CritTypes>0.0%L - 0.0%F - 0.0%M</CritTypes>
        <ThreatStr>+(0)0/-(0)0</ThreatStr>
        <ThreatDelta>0</ThreatDelta>
        <Job>Smn</Job>
        <ParryPct>40%</ParryPct>
        <BlockPct>0%</BlockPct>
        <IncToHit>88.24</IncToHit>
        <OverHealPct>0%</OverHealPct>
        <DirectHitPct>28.7%</DirectHitPct>
        <DirectHitCount>341</DirectHitCount>
        <CritDirectHitCount>68</CritDirectHitCount>
        <CritDirectHitPct>5.7%</CritDirectHitPct>
    </Row>
</EncounterTable>